{"loginId":"your_login_id","participantId":"your_participant_id","sceneName":"Tutorial","cameraPoses":[{"position":{"x":0.0,"y":0.0,"z":0.0},"orientation":{"x":0.0,"y":0.0,"z":0.0,"w":1.0},"timestamp":"2023-08-21T05:39:09.3739410Z"},{"position":{"x":0.0,"y":0.0,"z":0.0},"orientation":{"x":0.0,"y":0.0,"z":0.0,"w":1.0},"timestamp":"2023-08-21T05:39:09.4851858Z"},{"position":{"x":0.0,"y":0.0,"z":0.0},"orientation":{"x":0.0,"y":0.0,"z":0.0,"w":1.0},"timestamp":"2023-08-21T05:39:09.5969820Z"},{"position":{"x":0.0,"y":0.0,"z":0.0},"orientation":{"x":0.0,"y":0.0,"z":0.0,"w":1.0},"timestamp":"2023-08-21T05:39:09.7076333Z"},{"position":{"x":0.0,"y":0.0,"z":0.0},"orientation":{"x":0.0,"y":0.0,"z":0.0,"w":1.0},"timestamp":"2023-08-21T05:39:09.8196577Z"},{"position":{"x":0.0,"y":0.0,"z":0.0},"orientation":{"x":0.0,"y":0.0,"z":0.0,"w":1.0},"timestamp":"2023-08-21T05:39:09.9312234Z"},{"position":{"x":0.0,"y":0.0,"z":0.0},"orientation":{"x":0.0,"y":0.0,"z":0.0,"w":1.0},"timestamp":"2023-08-21T05:39:10.0412474Z"},{"position":{"x":0.0,"y":0.0,"z":0.0},"orientation":{"x":0.0,"y":0.0,"z":0.0,"w":1.0},"timestamp":"2023-08-21T05:39:10.1532418Z"},{"position":{"x":0.0,"y":0.0,"z":0.0},"orientation":{"x":0.0,"y":0.0,"z":0.0,"w":1.0},"timestamp":"2023-08-21T05:39:10.2648899Z"},{"position":{"x":0.0,"y":0.0,"z":0.0},"orientation":{"x":0.0,"y":0.0,"z":0.0,"w":1.0},"timestamp":"2023-08-21T05:39:10.3768976Z"},{"position":{"x":0.0,"y":0.0,"z":0.0},"orientation":{"x":0.0,"y":0.0,"z":0.0,"w":1.0},"timestamp":"2023-08-21T05:39:10.4878082Z"},{"position":{"x":0.0,"y":0.0,"z":0.0},"orientation":{"x":0.0,"y":0.0,"z":0.0,"w":1.0},"timestamp":"2023-08-21T05:39:10.5991111Z"},{"position":{"x":0.0,"y":0.0,"z":0.0},"orientation":{"x":0.0,"y":0.0,"z":0.0,"w":1.0},"timestamp":"2023-08-21T05:39:10.7103414Z"},{"position":{"x":0.0,"y":0.0,"z":0.0},"orientation":{"x":0.0,"y":0.0,"z":0.0,"w":1.0},"timestamp":"2023-08-21T05:39:10.8213337Z"},{"position":{"x":0.0,"y":0.0,"z":0.0},"orientation":{"x":0.0,"y":0.0,"z":0.0,"w":1.0},"timestamp":"2023-08-21T05:39:10.9331634Z"},{"position":{"x":0.0,"y":0.0,"z":0.0},"orientation":{"x":0.0,"y":0.0,"z":0.0,"w":1.0},"timestamp":"2023-08-21T05:39:11.0440262Z"},{"position":{"x":0.0,"y":0.0,"z":0.0},"orientation":{"x":0.0,"y":0.0,"z":0.0,"w":1.0},"timestamp":"2023-08-21T05:39:11.1565436Z"},{"position":{"x":0.0,"y":0.0,"z":0.0},"orientation":{"x":0.0,"y":0.0,"z":0.0,"w":1.0},"timestamp":"2023-08-21T05:39:11.2672291Z"},{"position":{"x":0.0,"y":0.0,"z":0.0},"orientation":{"x":0.0,"y":0.0,"z":0.0,"w":1.0},"timestamp":"2023-08-21T05:39:11.3788029Z"},{"position":{"x":0.0,"y":0.0,"z":0.0},"orientation":{"x":0.0,"y":0.0,"z":0.0,"w":1.0},"timestamp":"2023-08-21T05:39:11.4904789Z"},{"position":{"x":0.0,"y":0.0,"z":0.0},"orientation":{"x":0.0,"y":0.0,"z":0.0,"w":1.0},"timestamp":"2023-08-21T05:39:11.6019906Z"},{"position":{"x":0.0,"y":0.0,"z":0.0},"orientation":{"x":0.0,"y":0.0,"z":0.0,"w":1.0},"timestamp":"2023-08-21T05:39:11.7130386Z"},{"position":{"x":0.0,"y":0.0,"z":0.0},"orientation":{"x":0.0,"y":0.0,"z":0.0,"w":1.0},"timestamp":"2023-08-21T05:39:11.8239124Z"},{"position":{"x":0.0,"y":0.0,"z":0.0},"orientation":{"x":0.0,"y":0.0,"z":0.0,"w":1.0},"timestamp":"2023-08-21T05:39:11.9353536Z"},{"position":{"x":0.0,"y":0.0,"z":0.0},"orientation":{"x":0.0,"y":0.0,"z":0.0,"w":1.0},"timestamp":"2023-08-21T05:39:12.0472513Z"},{"position":{"x":0.0,"y":0.0,"z":0.0},"orientation":{"x":0.0,"y":0.0,"z":0.0,"w":1.0},"timestamp":"2023-08-21T05:39:12.1582364Z"},{"position":{"x":0.0,"y":0.0,"z":0.0},"orientation":{"x":0.0,"y":0.0,"z":0.0,"w":1.0},"timestamp":"2023-08-21T05:39:12.2709761Z"}]}