{"loginId":"-1","participantId":"1","sceneName":"Attic","cameraPoses":[{"position":{"x":0.0,"y":1.1175999641418458,"z":0.0},"orientation":{"x":0.0,"y":0.0,"z":0.0,"w":1.0},"timestamp":"2023-09-01T05:27:09.2162492Z"},{"position":{"x":0.0,"y":1.1175999641418458,"z":0.0},"orientation":{"x":0.0,"y":0.0,"z":0.0,"w":1.0},"timestamp":"2023-09-01T05:27:09.3166356Z"},{"position":{"x":0.0,"y":1.1175999641418458,"z":0.0},"orientation":{"x":0.0,"y":0.0,"z":0.0,"w":1.0},"timestamp":"2023-09-01T05:27:09.4180939Z"},{"position":{"x":0.0,"y":1.1175999641418458,"z":0.0},"orientation":{"x":0.0,"y":0.0,"z":0.0,"w":1.0},"timestamp":"2023-09-01T05:27:09.5199803Z"},{"position":{"x":0.0,"y":1.1175999641418458,"z":0.0},"orientation":{"x":0.0,"y":0.0,"z":0.0,"w":1.0},"timestamp":"2023-09-01T05:27:09.6199987Z"},{"position":{"x":0.0,"y":1.1175999641418458,"z":0.0},"orientation":{"x":0.0,"y":0.0,"z":0.0,"w":1.0},"timestamp":"2023-09-01T05:27:09.7201073Z"},{"position":{"x":0.0,"y":1.1175999641418458,"z":0.0},"orientation":{"x":0.0,"y":0.0,"z":0.0,"w":1.0},"timestamp":"2023-09-01T05:27:09.8221170Z"},{"position":{"x":0.0,"y":1.1175999641418458,"z":0.0},"orientation":{"x":0.0,"y":0.0,"z":0.0,"w":1.0},"timestamp":"2023-09-01T05:27:09.9220524Z"},{"position":{"x":0.0,"y":1.1175999641418458,"z":0.0},"orientation":{"x":0.0,"y":0.0,"z":0.0,"w":1.0},"timestamp":"2023-09-01T05:27:10.0230590Z"},{"position":{"x":0.0,"y":1.1175999641418458,"z":0.0},"orientation":{"x":0.0,"y":0.0,"z":0.0,"w":1.0},"timestamp":"2023-09-01T05:27:10.1229597Z"},{"position":{"x":0.0,"y":1.1175999641418458,"z":0.0},"orientation":{"x":0.0,"y":0.0,"z":0.0,"w":1.0},"timestamp":"2023-09-01T05:27:10.2241762Z"},{"position":{"x":0.0,"y":1.1175999641418458,"z":0.0},"orientation":{"x":0.0,"y":0.0,"z":0.0,"w":1.0},"timestamp":"2023-09-01T05:27:10.3256438Z"},{"position":{"x":0.0,"y":1.1175999641418458,"z":0.0},"orientation":{"x":0.0,"y":0.0,"z":0.0,"w":1.0},"timestamp":"2023-09-01T05:27:10.4256559Z"},{"position":{"x":0.0,"y":1.1175999641418458,"z":0.0},"orientation":{"x":0.0,"y":0.0,"z":0.0,"w":1.0},"timestamp":"2023-09-01T05:27:10.5263424Z"},{"position":{"x":0.0,"y":1.1175999641418458,"z":0.0},"orientation":{"x":0.0,"y":0.0,"z":0.0,"w":1.0},"timestamp":"2023-09-01T05:27:10.6265448Z"},{"position":{"x":0.0,"y":1.1175999641418458,"z":0.0},"orientation":{"x":0.0,"y":0.0,"z":0.0,"w":1.0},"timestamp":"2023-09-01T05:27:10.7271530Z"},{"position":{"x":0.0,"y":1.1175999641418458,"z":0.0},"orientation":{"x":0.0,"y":0.0,"z":0.0,"w":1.0},"timestamp":"2023-09-01T05:27:10.8269692Z"},{"position":{"x":0.0,"y":1.1175999641418458,"z":0.0},"orientation":{"x":0.0,"y":0.0,"z":0.0,"w":1.0},"timestamp":"2023-09-01T05:27:10.9263431Z"},{"position":{"x":0.0,"y":1.1175999641418458,"z":0.0},"orientation":{"x":0.0,"y":0.0,"z":0.0,"w":1.0},"timestamp":"2023-09-01T05:27:11.0279657Z"},{"position":{"x":0.0,"y":1.1175999641418458,"z":0.0},"orientation":{"x":0.0,"y":0.0,"z":0.0,"w":1.0},"timestamp":"2023-09-01T05:27:11.1280709Z"},{"position":{"x":0.0,"y":1.1175999641418458,"z":0.0},"orientation":{"x":0.0,"y":0.0,"z":0.0,"w":1.0},"timestamp":"2023-09-01T05:27:11.2296058Z"},{"position":{"x":0.0,"y":1.1175999641418458,"z":0.0},"orientation":{"x":0.0,"y":0.0,"z":0.0,"w":1.0},"timestamp":"2023-09-01T05:27:11.3314005Z"},{"position":{"x":0.0,"y":1.1175999641418458,"z":0.0},"orientation":{"x":0.0,"y":0.0,"z":0.0,"w":1.0},"timestamp":"2023-09-01T05:27:11.4323443Z"},{"position":{"x":0.0,"y":1.1175999641418458,"z":0.0},"orientation":{"x":0.0,"y":0.0,"z":0.0,"w":1.0},"timestamp":"2023-09-01T05:27:11.5327778Z"},{"position":{"x":0.0,"y":1.1175999641418458,"z":0.0},"orientation":{"x":0.0,"y":0.0,"z":0.0,"w":1.0},"timestamp":"2023-09-01T05:27:11.6343656Z"},{"position":{"x":0.0,"y":1.1175999641418458,"z":0.0},"orientation":{"x":0.0,"y":0.0,"z":0.0,"w":1.0},"timestamp":"2023-09-01T05:27:11.7352026Z"},{"position":{"x":0.0,"y":1.1175999641418458,"z":0.0},"orientation":{"x":0.0,"y":0.0,"z":0.0,"w":1.0},"timestamp":"2023-09-01T05:27:11.8359312Z"},{"position":{"x":0.0,"y":1.1175999641418458,"z":0.0},"orientation":{"x":0.0,"y":0.0,"z":0.0,"w":1.0},"timestamp":"2023-09-01T05:27:11.9359260Z"},{"position":{"x":0.0,"y":1.1175999641418458,"z":0.0},"orientation":{"x":0.0,"y":0.0,"z":0.0,"w":1.0},"timestamp":"2023-09-01T05:27:12.0369767Z"},{"position":{"x":0.0,"y":1.1175999641418458,"z":0.0},"orientation":{"x":0.0,"y":0.0,"z":0.0,"w":1.0},"timestamp":"2023-09-01T05:27:12.1379313Z"}]}